qtawk/__init__.py
qtawk/__main__.py
qtawk/core.py
qtawk/ico/128.txt
qtawk/ico/480.txt
qtawk/ico/Logo_Q.svg
qtawk/ico/Logo_Q_black.svg
qtawk/ico/Logo_Qtawk.svg
qtawk/ico/Logo_Qtawk.svg.png
qtawk/ico/logo-white.ico
qtawk/ico/logo_128.ico
qtawk/ico/logo_128.png
qtawk/ico/logo_128.txt
qtawk/ico/logo_32.ico
qtawk/ico/logo_32_v2.ico
qtawk/ico/logo_32_v3.ico
qtawk/ico/logo_32_v4.ico
qtawk/ico/logo_480.png
qtawk/ico/logo_64.ico
qtawk/man/cut.txt
qtawk/man/egrep.txt
qtawk/man/head.txt
qtawk/man/tail.txt
qtawk/scripts/count.awk
qtawk/scripts/histogram.awk
qtawk/scripts/max.awk
qtawk/scripts/mean.awk
qtawk/scripts/padding.awk
qtawk/scripts/remove_first_field.awk
qtawk/scripts/rot13.awk
qtawk/scripts/rot13_test.awk
qtawk/scripts/sum.awk
qtawk/scripts/table.awk
qtawk/scripts/transpose.awk
qtawk/ui/About.py
qtawk/ui/About.ui
qtawk/ui/AutoPadding.py
qtawk/ui/AutoPadding.ui
qtawk/ui/MainUi.py
qtawk/ui/MainUi.ui
qtawk/ui/Padding.py
qtawk/ui/Padding.ui
qtawk/ui/SelectColumns.py
qtawk/ui/SelectColumns.ui
qtawk/ui/Sort.py
qtawk/ui/Sort.ui
qtawk/ui/Substitute.py
qtawk/ui/Substitute.ui
qtawk/ui/about.html
qtawk/ui/ui2py.sh
qtawk-0.1.3.dist-info/entry_points.txt
qtawk-0.1.3.dist-info/LICENSE.txt
qtawk-0.1.3.dist-info/WHEEL
qtawk-0.1.3.dist-info/METADATA
qtawk-0.1.3.dist-info/RECORD
